{
  "products": [
    {
      "title": "2",
      "price": "2",
      "quantity": "2",
      "location": "2",
      "description": "2",
      "category": "2",
      "id": 2
    },
    {
      "title": "ㄴ",
      "price": "ㄴ",
      "quantity": "ㄴ",
      "location": "ㅁ",
      "description": "ㄴ",
      "category": "ㅋ",
      "id": 3
    },
    {
      "title": "11",
      "price": "11",
      "quantity": "11",
      "location": "1",
      "description": "1",
      "category": "1",
      "id": 4
    },
    {
      "title": "3",
      "price": "xs",
      "quantity": "f",
      "location": "e",
      "description": "x",
      "category": "f",
      "id": 6
    },
    {
      "title": "2",
      "price": "3",
      "quantity": "1",
      "location": "31",
      "description": "33",
      "category": "2",
      "id": 7
    },
    {
      "title": "s",
      "price": "s",
      "quantity": "s",
      "location": "s",
      "description": "s",
      "category": "a",
      "id": 8
    }
  ]
}